{
    "examples": [
        {
            "tokens": [
                "[CLS]",
                "not",
                "everything",
                "works",
                ",",
                "but",
                "the",
                "average",
                "is",
                "higher",
                "than",
                "in",
                "mary",
                "and",
                "most",
                "other",
                "recent",
                "comedies",
                ".",
                "[SEP]"
            ],
            "label": 1.0,
            "bounds": [
                {
                    "position": [
                        5,
                        10
                    ],
                    "eps": 0.0009521484375
                },
                {
                    "position": [
                        16,
                        17
                    ],
                    "eps": 0.0009521484375
                },
                {
                    "position": [
                        2,
                        8
                    ],
                    "eps": 0.0009411621093749999
                },
                {
                    "position": [
                        10,
                        17
                    ],
                    "eps": 0.00095458984375
                },
                {
                    "position": [
                        2,
                        17
                    ],
                    "eps": 0.000936279296875
                },
                {
                    "position": [
                        10,
                        13
                    ],
                    "eps": 0.0009606933593749999
                },
                {
                    "position": [
                        2,
                        18
                    ],
                    "eps": 0.000936279296875
                },
                {
                    "position": [
                        5,
                        8
                    ],
                    "eps": 0.000955810546875
                },
                {
                    "position": [
                        14,
                        15
                    ],
                    "eps": 0.0009423828125
                },
                {
                    "position": [
                        14,
                        16
                    ],
                    "eps": 0.0009509277343749999
                }
            ],
            "time": 1195.6684424877167
        },
        {
            "tokens": [
                "[CLS]",
                "for",
                "me",
                ",",
                "this",
                "opera",
                "is",
                "n",
                "'",
                "t",
                "a",
                "favorite",
                ",",
                "so",
                "it",
                "'",
                "s",
                "a",
                "long",
                "time",
                "before",
                "the",
                "fat",
                "lady",
                "sings",
                ".",
                "[SEP]"
            ],
            "label": 0.0,
            "bounds": [
                {
                    "position": [
                        15,
                        22
                    ],
                    "eps": 0.005336914062499999
                },
                {
                    "position": [
                        12,
                        16
                    ],
                    "eps": 0.005341796874999999
                },
                {
                    "position": [
                        10,
                        19
                    ],
                    "eps": 0.0053662109375
                },
                {
                    "position": [
                        7,
                        14
                    ],
                    "eps": 0.005249023437499999
                },
                {
                    "position": [
                        1,
                        10
                    ],
                    "eps": 0.005336914062499999
                },
                {
                    "position": [
                        2,
                        5
                    ],
                    "eps": 0.005239257812499999
                },
                {
                    "position": [
                        7,
                        17
                    ],
                    "eps": 0.005253906249999999
                },
                {
                    "position": [
                        18,
                        25
                    ],
                    "eps": 0.0053076171875
                },
                {
                    "position": [
                        20,
                        25
                    ],
                    "eps": 0.005327148437499999
                },
                {
                    "position": [
                        7,
                        21
                    ],
                    "eps": 0.005258789062499999
                }
            ],
            "time": 1970.8274295330048
        },
        {
            "tokens": [
                "[CLS]",
                "almost",
                "everything",
                "else",
                "is",
                "wan",
                ".",
                "[SEP]"
            ],
            "label": 0.0,
            "bounds": [
                {
                    "position": [
                        1,
                        6
                    ],
                    "eps": 0.00155029296875
                },
                {
                    "position": [
                        3,
                        6
                    ],
                    "eps": 0.001566162109375
                },
                {
                    "position": [
                        3,
                        5
                    ],
                    "eps": 0.001551513671875
                },
                {
                    "position": [
                        2,
                        6
                    ],
                    "eps": 0.0015563964843750002
                },
                {
                    "position": [
                        1,
                        4
                    ],
                    "eps": 0.001544189453125
                },
                {
                    "position": [
                        2,
                        3
                    ],
                    "eps": 0.00155029296875
                },
                {
                    "position": [
                        1,
                        3
                    ],
                    "eps": 0.00154296875
                },
                {
                    "position": [
                        1,
                        2
                    ],
                    "eps": 0.001534423828125
                },
                {
                    "position": [
                        4,
                        5
                    ],
                    "eps": 0.001552734375
                },
                {
                    "position": [
                        1,
                        5
                    ],
                    "eps": 0.0015356445312500002
                }
            ],
            "time": 429.4348316192627
        },
        {
            "tokens": [
                "[CLS]",
                "no",
                ",",
                "it",
                "'",
                "s",
                "not",
                "nearly",
                "as",
                "good",
                "as",
                "any",
                "of",
                "its",
                "influences",
                ".",
                "[SEP]"
            ],
            "label": 0.0,
            "bounds": [
                {
                    "position": [
                        1,
                        13
                    ],
                    "eps": 0.00469970703125
                },
                {
                    "position": [
                        2,
                        3
                    ],
                    "eps": 0.004929199218750001
                },
                {
                    "position": [
                        6,
                        7
                    ],
                    "eps": 0.0047753906250000006
                },
                {
                    "position": [
                        1,
                        6
                    ],
                    "eps": 0.004594726562500001
                },
                {
                    "position": [
                        6,
                        12
                    ],
                    "eps": 0.004726562500000001
                },
                {
                    "position": [
                        1,
                        15
                    ],
                    "eps": 0.004704589843750001
                },
                {
                    "position": [
                        13,
                        14
                    ],
                    "eps": 0.0048681640625
                },
                {
                    "position": [
                        6,
                        14
                    ],
                    "eps": 0.0047534179687500015
                },
                {
                    "position": [
                        7,
                        13
                    ],
                    "eps": 0.0048925781250000015
                },
                {
                    "position": [
                        2,
                        13
                    ],
                    "eps": 0.004851074218750001
                }
            ],
            "time": 1113.8632354736328
        },
        {
            "tokens": [
                "[CLS]",
                "daring",
                ",",
                "mesmerizing",
                "and",
                "exceeding",
                "##ly",
                "hard",
                "to",
                "forget",
                ".",
                "[SEP]"
            ],
            "label": 1.0,
            "bounds": [
                {
                    "position": [
                        2,
                        3
                    ],
                    "eps": 0.0012548828125000001
                },
                {
                    "position": [
                        7,
                        10
                    ],
                    "eps": 0.0012536621093750002
                },
                {
                    "position": [
                        4,
                        8
                    ],
                    "eps": 0.001265869140625
                },
                {
                    "position": [
                        1,
                        3
                    ],
                    "eps": 0.00125732421875
                },
                {
                    "position": [
                        2,
                        10
                    ],
                    "eps": 0.00125732421875
                },
                {
                    "position": [
                        8,
                        9
                    ],
                    "eps": 0.0012469482421875
                }
            ],
            "time": 425.3131945133209
        },
        {
            "tokens": [
                "[CLS]",
                "i",
                "watched",
                "the",
                "brain",
                "##less",
                "insanity",
                "of",
                "no",
                "such",
                "thing",
                "with",
                "mounting",
                "disbelief",
                ".",
                "[SEP]"
            ],
            "label": 0.0,
            "bounds": [
                {
                    "position": [
                        2,
                        9
                    ],
                    "eps": 0.00358154296875
                },
                {
                    "position": [
                        1,
                        13
                    ],
                    "eps": 0.003544921875
                },
                {
                    "position": [
                        1,
                        8
                    ],
                    "eps": 0.0035620117187499995
                },
                {
                    "position": [
                        6,
                        10
                    ],
                    "eps": 0.0035766601562499997
                },
                {
                    "position": [
                        9,
                        10
                    ],
                    "eps": 0.0035986328124999996
                },
                {
                    "position": [
                        3,
                        10
                    ],
                    "eps": 0.0036010742187499996
                },
                {
                    "position": [
                        8,
                        13
                    ],
                    "eps": 0.0035742187499999997
                },
                {
                    "position": [
                        3,
                        9
                    ],
                    "eps": 0.0036181640625
                }
            ],
            "time": 831.6428072452545
        },
        {
            "tokens": [
                "[CLS]",
                "za",
                "##ny",
                ",",
                "ex",
                "##uber",
                "##antly",
                "ir",
                "##re",
                "##vere",
                "##nt",
                "animated",
                "space",
                "adventure",
                ".",
                "[SEP]"
            ],
            "label": 1.0,
            "bounds": [],
            "time": 0.0064694881439208984
        },
        {
            "tokens": [
                "[CLS]",
                "loving",
                "##ly",
                "choreographed",
                "blood",
                "##shed",
                "taking",
                "place",
                "in",
                "a",
                "pristine",
                "movie",
                "never",
                "##land",
                ",",
                "basically",
                ".",
                "[SEP]"
            ],
            "label": 1.0,
            "bounds": [
                {
                    "position": [
                        15,
                        16
                    ],
                    "eps": 0.00341796875
                },
                {
                    "position": [
                        9,
                        11
                    ],
                    "eps": 0.0034838867187499995
                },
                {
                    "position": [
                        7,
                        16
                    ],
                    "eps": 0.0034741210937499997
                },
                {
                    "position": [
                        9,
                        15
                    ],
                    "eps": 0.0034301757812499997
                },
                {
                    "position": [
                        9,
                        10
                    ],
                    "eps": 0.0034912109374999993
                }
            ],
            "time": 575.9781200885773
        },
        {
            "tokens": [
                "[CLS]",
                "loving",
                "##ly",
                "choreographed",
                "blood",
                "##shed",
                "taking",
                "place",
                "in",
                "a",
                "pristine",
                "movie",
                "never",
                "##land",
                ",",
                "basically",
                ".",
                "[SEP]"
            ],
            "label": 1.0,
            "bounds": [
                {
                    "position": [
                        15,
                        16
                    ],
                    "eps": 0.00341796875
                },
                {
                    "position": [
                        9,
                        11
                    ],
                    "eps": 0.0034838867187499995
                },
                {
                    "position": [
                        7,
                        16
                    ],
                    "eps": 0.0034741210937499997
                },
                {
                    "position": [
                        9,
                        15
                    ],
                    "eps": 0.0034301757812499997
                },
                {
                    "position": [
                        9,
                        10
                    ],
                    "eps": 0.0034912109374999993
                }
            ],
            "time": 575.7279839515686
        },
        {
            "tokens": [
                "[CLS]",
                "de",
                "niro",
                "may",
                "enjoy",
                "the",
                "same",
                "free",
                "ride",
                "from",
                "critics",
                "afforded",
                "to",
                "clint",
                "eastwood",
                "in",
                "the",
                "lazy",
                "blood",
                "##work",
                ".",
                "[SEP]"
            ],
            "label": 0.0,
            "bounds": [
                {
                    "position": [
                        7,
                        10
                    ],
                    "eps": 0.00440185546875
                },
                {
                    "position": [
                        3,
                        10
                    ],
                    "eps": 0.00435791015625
                },
                {
                    "position": [
                        10,
                        12
                    ],
                    "eps": 0.004362792968750001
                },
                {
                    "position": [
                        6,
                        9
                    ],
                    "eps": 0.004350585937500001
                },
                {
                    "position": [
                        5,
                        7
                    ],
                    "eps": 0.0044140625000000005
                },
                {
                    "position": [
                        8,
                        20
                    ],
                    "eps": 0.0044140625000000005
                },
                {
                    "position": [
                        6,
                        16
                    ],
                    "eps": 0.00431396484375
                },
                {
                    "position": [
                        3,
                        9
                    ],
                    "eps": 0.00437744140625
                },
                {
                    "position": [
                        11,
                        13
                    ],
                    "eps": 0.00437744140625
                }
            ],
            "time": 1341.3509964942932
        }
    ],
    "minimum": 0.00282464599609375,
    "average": 0.002870956081814236
}